setup.py
pyassert/__init__.py
pyassert/assertionhandler.py
pyassert/list_matchers.py
pyassert/matcher_registry.py
pyassert/number_matchers.py
pyassert/object_matchers.py
pyassert/string_matchers.py
pyassert.egg-info/PKG-INFO
pyassert.egg-info/SOURCES.txt
pyassert.egg-info/dependency_links.txt
pyassert.egg-info/top_level.txt
pyassert.egg-info/zip-safe