Metadata-Version: 1.1
Name: pyassert
Version: 0.2.4
Summary: Rich assertions library for Python
Home-page: https://github.com/pyclectic/pyassert
Author: Alexander Metzner, Michael Gruber
Author-email: halimath.wilanthaou@gmail.com, aelgru@gmail.com
License: Apache Software License
Platform: UNKNOWN
Classifier: Development Status :: 4 - Beta
Classifier: Environment :: Other Environment
Classifier: Intended Audience :: Developers
Classifier: License :: OSI Approved :: Apache Software License
Classifier: Programming Language :: Python
Classifier: Programming Language :: Python :: 2.6
Classifier: Programming Language :: Python :: 2.7
Classifier: Programming Language :: Python :: 3.2
Classifier: Topic :: Software Development :: Quality Assurance
Classifier: Topic :: Software Development :: Testing
